{
    "paths": {
        "config": null,
        "gen_weights": null,
        "tiny_inet": null,
        "out_dir": null
    },
    "generator": {
        "img_size": [256, 256],
        "variant": "fc8"
    },
    "mask_generator": {
        "template": "TFFFF",
        "shuffle": false
    },
    "subject": {
        "rec_layers": [19, 21]
    },
    "scorer": {
        "target_layers": [19,21],
        "target_units": [[2, 3], [0, 4]],
        "aggregation": "mean",
        "rseed": 31415
    },
    "optimizer": {
        "pop_sz": 20,
        "rseed": 123,
        "mutation_rate": 0.3,
        "mutation_size": 0.3,
        "num_parents": 3,
        "temperature": 1.0,
        "random_state": "normal"
    },
    "logger": {
        "name": "experiment",
        "version": null
    },
    "num_gens": 50
}